MANIFEST.in
README.md
_screenshot.png
requirements.txt
setup.py
signalum.png
Signalum.egg-info/PKG-INFO
Signalum.egg-info/SOURCES.txt
Signalum.egg-info/dependency_links.txt
Signalum.egg-info/not-zip-safe
Signalum.egg-info/requires.txt
Signalum.egg-info/top_level.txt
signalum/__init__.py
signalum/_version.py
signalum/cli.py
signalum/core/__init__.py
signalum/core/_all.py
signalum/core/_base.py
signalum/core/_bluetooth.py
signalum/core/_exceptions.py
signalum/core/_wifi.py
signalum/core/utils.py
signalum/scripts/signalyze
signalum/tests/__init__.py