Metadata-Version: 2.1
Name: Signalum
Version: 0.0.8
Summary: Package to analyze existing connections from wifi and bluetooth
Home-page: https://github.com/bisoncorps/signalum
Author: Domnan Diretnan, Mmadu Manasseh
Author-email: diretnandomnan@gmail.com
License: MIT
Keywords: bluetooth detect wifi multiprotocol
Platform: UNKNOWN
Classifier: Programming Language :: Python :: 3
Classifier: License :: OSI Approved :: MIT License
Classifier: Operating System :: POSIX
